scikit_neuromsi-1.0.2.dist-info/licenses/LICENSE.txt
skneuromsi/__init__.py
skneuromsi/io.py
skneuromsi/sweep.py
skneuromsi/testing.py
skneuromsi/bayesian/__init__.py
skneuromsi/bayesian/_kording2007.py
skneuromsi/bayesian/_zhu2024.py
skneuromsi/core/__init__.py
skneuromsi/core/constants.py
skneuromsi/core/modelabc.py
skneuromsi/core/ndresult/__init__.py
skneuromsi/core/ndresult/compress.py
skneuromsi/core/ndresult/plot_acc.py
skneuromsi/core/ndresult/result.py
skneuromsi/core/ndresult/stats_acc.py
skneuromsi/mle/__init__.py
skneuromsi/mle/_alais_burr2004.py
skneuromsi/ndcollection/__init__.py
skneuromsi/ndcollection/bias_acc.py
skneuromsi/ndcollection/causes_acc.py
skneuromsi/ndcollection/collection.py
skneuromsi/ndcollection/cplot_acc.py
skneuromsi/neural/__init__.py
skneuromsi/neural/_cuppini2014.py
skneuromsi/neural/_cuppini2017.py
skneuromsi/neural/_paredes2025.py
skneuromsi/utils/__init__.py
skneuromsi/utils/accabc.py
skneuromsi/utils/bunch.py
skneuromsi/utils/custom_json.py
skneuromsi/utils/ddtype_tools.py
skneuromsi/utils/dict_cmp.py
skneuromsi/utils/doctools.py
skneuromsi/utils/memtools.py
skneuromsi/utils/neural_tools.py
skneuromsi/utils/readout_tools.py
scikit_neuromsi-1.0.2.dist-info/METADATA
scikit_neuromsi-1.0.2.dist-info/WHEEL
scikit_neuromsi-1.0.2.dist-info/top_level.txt
scikit_neuromsi-1.0.2.dist-info/RECORD
