Metadata-Version: 2.4
Name: scikit-neuromsi
Version: 1.0.2
Summary: Implementation of multisensory integration models in Python
Author-email: Renato Paredes <paredesrenato92@gmail.com>, "Juan B. Cabral" <jbcabral@unc.edu.ar>
License: Copyright (c) 2021, Paredes, Renato; Cabral, Juan
Project-URL: Homepage, https://github.com/renatoparedes/scikit-neuromsi
Project-URL: Repository, https://github.com/renatoparedes/scikit-neuromsi
Keywords: multisensory integration,computational neuroscience,cognitive modelling,behaviour simulation,perception
Classifier: Development Status :: 4 - Beta
Classifier: Intended Audience :: Education
Classifier: Intended Audience :: Science/Research
Classifier: License :: OSI Approved :: BSD License
Classifier: Operating System :: OS Independent
Classifier: Programming Language :: Python
Classifier: Programming Language :: Python :: 3
Classifier: Programming Language :: Python :: 3.10
Classifier: Programming Language :: Python :: 3.11
Classifier: Programming Language :: Python :: 3.12
Classifier: Programming Language :: Python :: 3.13
Classifier: Programming Language :: Python :: Implementation :: CPython
Classifier: Topic :: Scientific/Engineering
Requires-Python: >=3.10
License-File: LICENSE.txt
Requires-Dist: numpy
Requires-Dist: brainpy
Requires-Dist: scipy
Requires-Dist: jaxlib
Requires-Dist: jax
Requires-Dist: joblib
Requires-Dist: bidict
Requires-Dist: seaborn
Requires-Dist: xarray
Requires-Dist: tqdm
Requires-Dist: methodtools
Requires-Dist: netcdf4
Requires-Dist: custom_inherit
Requires-Dist: jinja2
Requires-Dist: humanize
Requires-Dist: pympler
Requires-Dist: psutil
Requires-Dist: lz4
Dynamic: license-file
